reelib/__init__.py
reelib/jsonctl.py
reelib/timestamp.py
reelib/vision.py
reelib-1.4.1.dist-info/LICENSE
reelib-1.4.1.dist-info/WHEEL
reelib-1.4.1.dist-info/METADATA
reelib-1.4.1.dist-info/RECORD
