Metadata-Version: 2.1
Name: reelib
Version: 1.4.1
Summary: 頻繁に利用する処理を集めたライブラリ
Home-page: https://github.com/reeve0930/reelib
License: MIT
Author: reeve0930
Author-email: reeve0930@gmail.com
Requires-Python: >=3.6,<4.0
Classifier: License :: OSI Approved :: MIT License
Classifier: Programming Language :: Python :: 3
Classifier: Programming Language :: Python :: 3.6
Classifier: Programming Language :: Python :: 3.7
Classifier: Programming Language :: Python :: 3.8
Requires-Dist: numpy (>=1.18.3,<2.0.0)
Requires-Dist: opencv-python (>=4.2.0,<5.0.0)
Requires-Dist: pillow (>=7.1.2,<8.0.0)
Project-URL: Repository, https://github.com/reeve0930/reelib
